autodiff/__init__.py
autodiff/autodiff.py
autodiff/visualizer.py
autodiffvis_teapeople-0.0.5.dist-info/LICENSE
autodiffvis_teapeople-0.0.5.dist-info/METADATA
autodiffvis_teapeople-0.0.5.dist-info/WHEEL
autodiffvis_teapeople-0.0.5.dist-info/top_level.txt
autodiffvis_teapeople-0.0.5.dist-info/RECORD
