Metadata-Version: 2.1
Name: autodiffvis-teapeople
Version: 0.0.5
Summary: This package implements automatic differentiation with visualization of the forward computation graph.
Home-page: https://github.com/cs107-theteapeople/cs107-FinalProject
Author: David Berthiaume, Lily Qian, Angel Hsu, Maggie Wu
Author-email: dberthiaume@g.harvard.edu, sqian@g.harvard.edu, angelyinhuahsu@g.harvard.edu, yitong_wu@g.harvard.edu
License: UNKNOWN
Project-URL: Documentation, https://github.com/cs107-theteapeople/cs107-FinalProject/blob/main/docs/milestone2.md
Platform: UNKNOWN
Classifier: Programming Language :: Python :: 3
Classifier: License :: OSI Approved :: GNU General Public License v3 (GPLv3)
Classifier: Operating System :: OS Independent
Requires-Python: >=3.6
License-File: LICENSE
Requires-Dist: numpy (>=1.20.3)
Requires-Dist: matplotlib (>=3.4.3)
Requires-Dist: imageio (>=2.9.0)
Provides-Extra: testing
Requires-Dist: pytest ; extra == 'testing'
